LICENSE
MANIFEST.in
README.md
setup.py
bin/secureshare-control
secureshare/__init__.py
secureshare/server.py
secureshare.egg-info/PKG-INFO
secureshare.egg-info/SOURCES.txt
secureshare.egg-info/dependency_links.txt
secureshare.egg-info/requires.txt
secureshare.egg-info/top_level.txt
secureshare/resources/sql/stor.add.sql
secureshare/resources/sql/stor.delete.expired.sql
secureshare/resources/sql/stor.delete.sql
secureshare/resources/sql/stor.expire.sql
secureshare/resources/sql/stor.get.sql
secureshare/resources/sql/token.add.sql
secureshare/resources/sql/token.delete.expired.sql
secureshare/resources/sql/token.delete.sql
secureshare/resources/sql/token.get.sql