Metadata-Version: 2.1
Name: secureshare
Version: 0.0.21
Summary: Secure share
Home-page: https://github.com/alttch/secureshare
Author: Altertech
Author-email: pr@altertech.com
License: Apache License 2.0
Platform: UNKNOWN
Classifier: Programming Language :: Python :: 3
Classifier: License :: OSI Approved :: Apache Software License
Classifier: Topic :: Communications
License-File: LICENSE
